{"orderData":{"shipments":[{"shipTo":{"name":"Nick Pope","address1":"73 STATION ROAD","address2":"","address3":"","town":"MICKLEOVER","state":"","postcode":"DE3 9GJ","isoCountry":"GB","country":"United Kingdom","email":"npope1@hotmail.com","companyName":"","phone":"07817293883"},"carrier":{"alias":"chateau.hermes.uk.24"},"attachments":[],"shipmentIndex":0,"pspBranding":true,"canShipEarly":true}],"items":[{"components":[{"fetch":true,"localFile":false,"attributes":{"Substrate":"Mini Apron"},"extraData":[],"code":"Apron","path":"ftp:\/\/ChateauFTP1:9Ha83aUF6p1@ftp.espsmile.co.uk\/array1\/FTPRoot\/000013342-01.pdf","componentId":"000013342A0101","barcode":"000013342A0101"}],"shipmentIndex":0,"sourceItemId":"0000133420101","quantity":1,"extraData":[],"sku":"Apron-Chateau","barcode":"0000133420101","unitWeight":350}],"stockItems":[],"error":[],"extraData":[],"printType":"digital","sourceOrderId":"000013342","email":"","amount":0,"customerName":"Le Chateau"},"destination":{"name":"hp.espcolour"}}